LICENSE.txt
README.md
setup.cfg
setup.py
roadmaptools/__init__.py
roadmaptools/adjectancy.py
roadmaptools/calculate_curvature.py
roadmaptools/clean_geojson.py
roadmaptools/common.py
roadmaptools/compute_edge_parameters.py
roadmaptools/const.py
roadmaptools/download_map.py
roadmaptools/estimate_speed_from_osm.py
roadmaptools/export_nodes_and_id_maker.py
roadmaptools/filter.py
roadmaptools/generate_config.py
roadmaptools/geojson_linestrings.py
roadmaptools/geojson_shp.py
roadmaptools/geometry.py
roadmaptools/gmaps.py
roadmaptools/gpx.py
roadmaptools/gpx_ load_test.py
roadmaptools/gpx_shp.py
roadmaptools/graph.py
roadmaptools/init.py
roadmaptools/inout.py
roadmaptools/osmfilter.py
roadmaptools/plotting.py
roadmaptools/prepare_geojson_to_agentpolisdemo.py
roadmaptools/printer.py
roadmaptools/road_graph_rtree.py
roadmaptools/road_structures.py
roadmaptools/sanitize.py
roadmaptools/shp.py
roadmaptools/simplify_graph.py
roadmaptools/utm.py
roadmaptools.egg-info/PKG-INFO
roadmaptools.egg-info/SOURCES.txt
roadmaptools.egg-info/dependency_links.txt
roadmaptools.egg-info/requires.txt
roadmaptools.egg-info/top_level.txt
roadmaptools/config/__init__.py
roadmaptools/config/cities_envelopes_item.py
roadmaptools/config/roadmaptools_config.py
roadmaptools/resources/__init__.py
roadmaptools/resources/config.cfg
roadmaptools/test/__init__.py
roadmaptools/test/angle_test.py
roadmaptools/test/big_map_test.py
roadmaptools/test/cut_trace.py
roadmaptools/test/distance_test.py
roadmaptools/test/int.py
roadmaptools/test/networkx_pickle_test.py
roadmaptools/test/shapely_project_test.py
roadmaptools/test/shp_test.py
roadmaptools/test/test_tmp.py