Metadata-Version: 2.1
Name: roadmaptools
Version: 5.0.0
Summary: Tools for road graph processing
Home-page: https://github.com/aicenter/roadmap-processing
Author: David Fiedler, Martin Korytak
Author-email: david.fiedler@agents.fel.cvut.cz
License: MIT
Platform: UNKNOWN
Requires-Python: >=3
License-File: LICENSE.txt
